mycalc/__init__.py
minyeop-0.0.1.dist-info/METADATA
minyeop-0.0.1.dist-info/WHEEL
minyeop-0.0.1.dist-info/top_level.txt
minyeop-0.0.1.dist-info/RECORD
